usageflow/fastapi/__init__.py
usageflow_fastapi-0.3.4.dist-info/METADATA
usageflow_fastapi-0.3.4.dist-info/WHEEL
usageflow_fastapi-0.3.4.dist-info/top_level.txt
usageflow_fastapi-0.3.4.dist-info/RECORD
