Metadata-Version: 2.4
Name: usageflow-fastapi
Version: 0.3.4
Summary: FastAPI middleware for UsageFlow - Usage-based pricing made simple
Home-page: https://github.com/usageflow/usageflow-python
Author: UsageFlow
Author-email: ronen@usageflow.io
Classifier: Development Status :: 4 - Beta
Classifier: Framework :: FastAPI
Classifier: Intended Audience :: Developers
Classifier: License :: OSI Approved :: MIT License
Classifier: Operating System :: OS Independent
Classifier: Programming Language :: Python :: 3
Classifier: Programming Language :: Python :: 3.6
Classifier: Programming Language :: Python :: 3.7
Classifier: Programming Language :: Python :: 3.8
Classifier: Programming Language :: Python :: 3.9
Classifier: Topic :: Software Development :: Libraries :: Python Modules
Requires-Python: >=3.6
Requires-Dist: fastapi>=0.68.0
Requires-Dist: usageflow-core>=0.3.4
Dynamic: author
Dynamic: author-email
Dynamic: classifier
Dynamic: description
Dynamic: description-content-type
Dynamic: home-page
Dynamic: requires-dist
Dynamic: requires-python
Dynamic: summary
